{"rentbase-api-dev":{"label":"rentbase-api-dev","status":"development deployed Fri Aug 12 11:10:21 UTC 2022","color":"0504cd"},"rentbase-portal":{"label":"rentbase-portal","status":"staging deployed Fri Aug 12 09:55:38 UTC 2022","color":"CD0504"},"rentbase-portal-prod":{"label":"rentbase-portal-prod","status":"master deployed Thu Aug 11 07:09:06 UTC 2022","color":"04CD05"},"rentbase-portal-dev":{"label":"rentbase-portal-dev","status":"development deployed Fri Aug 12 12:27:50 UTC 2022","color":"0504cd"},"rentbase-api":{"label":"rentbase-api","status":"staging deployed Tue Aug  9 12:20:21 UTC 2022","color":"CD0504"},"rentbase-api-prod":{"label":"rentbase-api-prod","status":"master deployed Thu Aug 11 06:54:36 UTC 2022","color":"04CD05"},"rentbase-admin-prod":{"label":"rentbase-admin-prod","status":"master deployed Fri Aug  5 22:08:20 UTC 2022","color":"04CD05"}}